{
    "key": "group_65e96807066f6",
    "title": "Mega menu",
    "fields": [
        {
            "key": "field_65e9680792cf2",
            "label": "Menu items",
            "name": "mega_menu_items",
            "aria-label": "",
            "type": "repeater",
            "instructions": "",
            "required": 0,
            "conditional_logic": 0,
            "wrapper": {
                "width": "",
                "class": "",
                "id": ""
            },
            "layout": "row",
            "pagination": 0,
            "min": 0,
            "max": 0,
            "collapsed": "",
            "button_label": "Add Item",
            "rows_per_page": 20,
            "sub_fields": [
                {
                    "key": "field_65e9688016f5c",
                    "label": "Title",
                    "name": "title",
                    "aria-label": "",
                    "type": "text",
                    "instructions": "",
                    "required": 1,
                    "conditional_logic": 0,
                    "wrapper": {
                        "width": "",
                        "class": "",
                        "id": ""
                    },
                    "default_value": "",
                    "maxlength": "",
                    "placeholder": "",
                    "prepend": "",
                    "append": "",
                    "parent_repeater": "field_65e9680792cf2"
                },
                {
                    "key": "field_65e96c4606ba1",
                    "label": "Link",
                    "name": "link",
                    "aria-label": "",
                    "type": "link",
                    "instructions": "",
                    "required": 1,
                    "conditional_logic": [
                        [
                            {
                                "field": "field_65e96bf006ba0",
                                "operator": "!=",
                                "value": "1"
                            }
                        ]
                    ],
                    "wrapper": {
                        "width": "",
                        "class": "",
                        "id": ""
                    },
                    "return_format": "array",
                    "parent_repeater": "field_65e9680792cf2"
                },
                {
                    "key": "field_65e96bf006ba0",
                    "label": "Add submenu",
                    "name": "add_submenu",
                    "aria-label": "",
                    "type": "true_false",
                    "instructions": "",
                    "required": 0,
                    "conditional_logic": 0,
                    "wrapper": {
                        "width": "",
                        "class": "",
                        "id": ""
                    },
                    "message": "",
                    "default_value": 0,
                    "ui": 0,
                    "ui_on_text": "",
                    "ui_off_text": "",
                    "parent_repeater": "field_65e9680792cf2"
                },
                {
                    "key": "field_65e96d4e06ba6",
                    "label": "Submenu columns count",
                    "name": "submenu_columns_count",
                    "aria-label": "",
                    "type": "select",
                    "instructions": "",
                    "required": 0,
                    "conditional_logic": [
                        [
                            {
                                "field": "field_65e96bf006ba0",
                                "operator": "==",
                                "value": "1"
                            }
                        ]
                    ],
                    "wrapper": {
                        "width": "",
                        "class": "",
                        "id": ""
                    },
                    "choices": {
                        "2": "Two columns",
                        "3": "Three columns",
                        "4": "Four columns"
                    },
                    "default_value": false,
                    "return_format": "value",
                    "multiple": 0,
                    "allow_null": 0,
                    "ui": 0,
                    "ajax": 0,
                    "placeholder": "",
                    "parent_repeater": "field_65e9680792cf2"
                },
                {
                    "key": "field_65e96c8606ba2",
                    "label": "Submenu items",
                    "name": "submenu_items",
                    "aria-label": "",
                    "type": "repeater",
                    "instructions": "",
                    "required": 0,
                    "conditional_logic": [
                        [
                            {
                                "field": "field_65e96bf006ba0",
                                "operator": "==",
                                "value": "1"
                            }
                        ]
                    ],
                    "wrapper": {
                        "width": "",
                        "class": "",
                        "id": ""
                    },
                    "layout": "table",
                    "min": 0,
                    "max": 0,
                    "collapsed": "",
                    "button_label": "Add Subitem",
                    "rows_per_page": 20,
                    "sub_fields": [
                        {
                            "key": "field_65e96cee06ba4",
                            "label": "Title",
                            "name": "title",
                            "aria-label": "",
                            "type": "text",
                            "instructions": "",
                            "required": 1,
                            "conditional_logic": 0,
                            "wrapper": {
                                "width": "",
                                "class": "",
                                "id": ""
                            },
                            "default_value": "",
                            "maxlength": "",
                            "placeholder": "",
                            "prepend": "",
                            "append": "",
                            "parent_repeater": "field_65e96c8606ba2"
                        },
                        {
                            "key": "field_65e96ec388d85",
                            "label": "Description",
                            "name": "description",
                            "aria-label": "",
                            "type": "textarea",
                            "instructions": "",
                            "required": 1,
                            "conditional_logic": 0,
                            "wrapper": {
                                "width": "",
                                "class": "",
                                "id": ""
                            },
                            "default_value": "Lorem Ipsum is simply dummy text of the printing and typesetting industry. Lorem Ipsum has been the industry's standard dummy text ever since the 1500s, when an unknown printer took a galley",
                            "maxlength": "",
                            "rows": "",
                            "placeholder": "",
                            "new_lines": "",
                            "parent_repeater": "field_65e96c8606ba2"
                        },
                        {
                            "key": "field_65e96cf706ba5",
                            "label": "Link",
                            "name": "link",
                            "aria-label": "",
                            "type": "link",
                            "instructions": "",
                            "required": 1,
                            "conditional_logic": 0,
                            "wrapper": {
                                "width": "",
                                "class": "",
                                "id": ""
                            },
                            "return_format": "array",
                            "parent_repeater": "field_65e96c8606ba2"
                        },
                        {
                            "key": "field_65e96ca806ba3",
                            "label": "Image",
                            "name": "image",
                            "aria-label": "",
                            "type": "image",
                            "instructions": "",
                            "required": 1,
                            "conditional_logic": 0,
                            "wrapper": {
                                "width": "",
                                "class": "",
                                "id": ""
                            },
                            "return_format": "id",
                            "library": "all",
                            "min_width": "",
                            "min_height": "",
                            "min_size": "",
                            "max_width": "",
                            "max_height": "",
                            "max_size": "",
                            "mime_types": "",
                            "preview_size": "thumbnail",
                            "parent_repeater": "field_65e96c8606ba2"
                        }
                    ],
                    "parent_repeater": "field_65e9680792cf2"
                }
            ]
        }
    ],
    "location": [
        [
            {
                "param": "options_page",
                "operator": "==",
                "value": "mega-menu-settings"
            }
        ]
    ],
    "menu_order": 0,
    "position": "normal",
    "style": "default",
    "label_placement": "top",
    "instruction_placement": "label",
    "hide_on_screen": "",
    "active": true,
    "description": "",
    "show_in_rest": 0,
    "modified": 1709807128
}